README.md
setup.py
alink.egg-info/PKG-INFO
alink.egg-info/SOURCES.txt
alink.egg-info/dependency_links.txt
alink.egg-info/entry_points.txt
alink.egg-info/not-zip-safe
alink.egg-info/requires.txt
alink.egg-info/top_level.txt
hugo/__init__.py
hugo/hugo.py
tests/__init__.py