Metadata-Version: 2.1
Name: alink
Version: 0.0.6
Summary: Bring users directly to specific content in your Android app.
Home-page: http://refactor.cn/
Author: andyxialm
Author-email: andyxialm@gmail.com
License: UNKNOWN
Platform: any
Classifier: Programming Language :: Python :: 3
Classifier: License :: OSI Approved :: MIT License
Classifier: Operating System :: OS Independent
Requires-Python: >=3.3
